MANIFEST.in
README.rst
setup.py
test-broken-apt-versioning.sh
vdt/__init__.py
vdt.versionplugin.hotfix.egg-info/PKG-INFO
vdt.versionplugin.hotfix.egg-info/SOURCES.txt
vdt.versionplugin.hotfix.egg-info/dependency_links.txt
vdt.versionplugin.hotfix.egg-info/namespace_packages.txt
vdt.versionplugin.hotfix.egg-info/requires.txt
vdt.versionplugin.hotfix.egg-info/top_level.txt
vdt.versionplugin.hotfix.egg-info/zip-safe
vdt/versionplugin/__init__.py
vdt/versionplugin/hotfix/__init__.py
vdt/versionplugin/hotfix/args.py
vdt/versionplugin/hotfix/package.py
vdt/versionplugin/hotfix/version.py