Metadata-Version: 1.0
Name: vdt.versionplugin.hotfix
Version: 0.0.7
Summary: Create hotfix packages, these add an iteration on an existing version and do not create a tag.
Home-page: https://github.com/devopsconsulting/vdt.versionplugin.hotfix
Author: Lars van de Kerkhof
Author-email: lars@permanentmarkers.nl
License: UNKNOWN
Platform: UNKNOWN
